zipkin/utils.py
zipkin/id_generator.py
zipkin/zipkin_data.py
zipkin/data_store.py
zipkin/scribe_writer.py
zipkin/__init__.py
zipkin/api.py
zipkin/tests/test_pep8.py
zipkin/tests/test_data_store.py
zipkin/tests/helpers.py
zipkin/tests/test_zipkin_data.py
zipkin/tests/test_id_generator.py
zipkin/tests/test_api.py
zipkin/tests/__init__.py
zipkin/_thrift/__init__.py
zipkin/_thrift/zipkinCore/ttypes.py
zipkin/_thrift/zipkinCore/constants.py
zipkin/_thrift/zipkinCore/__init__.py
zipkin/_thrift/scribe/ttypes.py
zipkin/_thrift/scribe/Scribe.py
zipkin/_thrift/scribe/constants.py
zipkin/_thrift/scribe/__init__.py
zipkin/_thrift/zipkinDependencies/ttypes.py
zipkin/_thrift/zipkinDependencies/constants.py
zipkin/_thrift/zipkinDependencies/__init__.py
zipkin-0.1.0.dist-info/DESCRIPTION.rst
zipkin-0.1.0.dist-info/RECORD
zipkin-0.1.0.dist-info/top_level.txt
zipkin-0.1.0.dist-info/WHEEL
zipkin-0.1.0.dist-info/metadata.json
zipkin-0.1.0.dist-info/METADATA
