Metadata-Version: 2.0
Name: zipkin
Version: 0.1.0
Summary: python api for sending data to Zipkin
Home-page: https://github.com/prezi/python-zipkin
Author: Zoltan Nagy, Zsolt Dollenstein
Author-email: zoltan.nagy@prezi.com, zsolt.dollenstein@prezi.com
License: Apache2
Keywords: zipkin python
Platform: any
Classifier: Development Status :: 4 - Beta
Classifier: Environment :: Web Environment
Classifier: Intended Audience :: Developers
Classifier: License :: Freely Distributable
Classifier: Operating System :: OS Independent
Classifier: Programming Language :: Python
Classifier: Programming Language :: Python :: 2
Classifier: Programming Language :: Python :: 2.6
Classifier: Programming Language :: Python :: 2.7
Classifier: Topic :: Software Development :: Libraries :: Application Frameworks
Classifier: Topic :: Software Development :: Libraries :: Python Modules
Requires-Dist: thrift (>=0.9.1)
